magolib/__init__.py
magolib/magolib.py
magolib-0.0.1.dist-info/LICENSE
magolib-0.0.1.dist-info/METADATA
magolib-0.0.1.dist-info/WHEEL
magolib-0.0.1.dist-info/top_level.txt
magolib-0.0.1.dist-info/RECORD
