Metadata-Version: 2.1
Name: magolib
Version: 0.0.1
Summary: A library to format and convert numbers in the Mago unit of measure
Author-email: Alessandro Sartori <alex.sartori1997@gmail.com>
License: Copyright (c) 2024 Alessandro Sartori
Project-URL: Homepage, https://github.com/AlexSartori/magolib
Project-URL: Repository, https://github.com/AlexSartori/magolib
Project-URL: Issues, https://github.com/AlexSartori/magolib/issues
Keywords: mago,unit of measure,format,convert
License-File: LICENSE
